{"location":{"lat":2.8545336057404724,"lng":0.8378106390669671},"accuracy":80,"macAddress":"0F:D4:B0:BA:54:4C","sessionId":"5qqwfwwfyyom18lh","session_start_timestamp":1681363779379,"timestamp":1681363779379,"devicebrand":"Apple","speed":"154 km/h"}
{"location":{"lat":7.830892512087429,"lng":5.740472842395383},"accuracy":30,"macAddress":"22:31:0C:4A:EF:ED","sessionId":"e77kg5hye4m5kc5a","session_start_timestamp":1681363780373,"timestamp":1681363780373,"devicebrand":"Xiaomi","speed":"17 km/h"}
{"location":{"lat":1.0616248700122743,"lng":2.2101430237320874},"accuracy":10,"macAddress":"8A:BB:DE:2E:29:4B","sessionId":"r9a2poiv0zhkebn0","session_start_timestamp":1681363780857,"timestamp":1681363780857,"devicebrand":"LG","speed":"31 km/h"}
{"location":{"lat":6.8115209821740414,"lng":8.324534986386428},"accuracy":110,"macAddress":"F0:B0:31:DD:7C:AA","sessionId":"10i3rlvryqdhqfgl","session_start_timestamp":1681363781292,"timestamp":1681363781292,"devicebrand":"Huawei","speed":"117 km/h"}
{"location":{"lat":5.665395584619168,"lng":8.166217994351761},"accuracy":50,"macAddress":"4C:45:65:67:37:71","sessionId":"l879tsheok7hskk4","session_start_timestamp":1681363781702,"timestamp":1681363781702,"devicebrand":"Oppo","speed":"141 km/h"}
{"location":{"lat":7.377079048566637,"lng":9.142874958895902},"accuracy":80,"macAddress":"F7:70:5E:39:C9:06","sessionId":"sstgatr9ezd6lo14","session_start_timestamp":1681363781890,"timestamp":1681363781890,"devicebrand":"Apple","speed":"155 km/h"}
{"location":{"lat":7.16466208177491,"lng":9.088204185189904},"accuracy":70,"macAddress":"13:BD:B0:D8:2B:35","sessionId":"8ihg17mj18xpbwxf","session_start_timestamp":1681363782283,"timestamp":1681363782283,"devicebrand":"Apple","speed":"85 km/h"}
{"location":{"lat":3.1766824077595257,"lng":2.2560786094211727},"accuracy":80,"macAddress":"11:C3:32:C1:10:3D","sessionId":"ff0mu58r724kydod","session_start_timestamp":1681363782786,"timestamp":1681363782786,"devicebrand":"Sony","speed":"71 km/h"}
{"location":{"lat":2.696229344573149,"lng":6.18573422643911},"accuracy":70,"macAddress":"E5:0E:29:AF:45:A3","sessionId":"in1fiffyjjfwr8rb","session_start_timestamp":1681363782964,"timestamp":1681363782964,"devicebrand":"Xiaomi","speed":"68 km/h"}
{"location":{"lat":0.3197462517770089,"lng":6.8252186106562025},"accuracy":70,"macAddress":"1D:CD:E5:1F:87:2B","sessionId":"e0yc68wcn718xkhs","session_start_timestamp":1681363783958,"timestamp":1681363783958,"devicebrand":"Oppo","speed":"153 km/h"}
{"location":{"lat":1.0607878449937045,"lng":2.2106097438594636},"accuracy":20,"macAddress":"8A:BB:DE:2E:29:4B","sessionId":"r9a2poiv0zhkebn0","session_start_timestamp":1681363780857,"timestamp":1681363784676,"devicebrand":"LG","speed":"31 km/h"}
{"location":{"lat":3.1757562223480535,"lng":2.2570551676034523},"accuracy":75,"macAddress":"11:C3:32:C1:10:3D","sessionId":"ff0mu58r724kydod","session_start_timestamp":1681363782786,"timestamp":1681363784764,"devicebrand":"Sony","speed":"71 km/h"}
{"location":{"lat":6.811881110938508,"lng":8.325469429173378},"accuracy":110,"macAddress":"F0:B0:31:DD:7C:AA","sessionId":"10i3rlvryqdhqfgl","session_start_timestamp":1681363781292,"timestamp":1681363785045,"devicebrand":"Huawei","speed":"117 km/h"}
{"location":{"lat":3.1765706812275956,"lng":2.256438269510755},"accuracy":90,"macAddress":"11:C3:32:C1:10:3D","sessionId":"ff0mu58r724kydod","session_start_timestamp":1681363782786,"timestamp":1681363785069,"devicebrand":"Sony","speed":"71 km/h"}
{"location":{"lat":6.811239074254734,"lng":8.326411624925335},"accuracy":100,"macAddress":"F0:B0:31:DD:7C:AA","sessionId":"10i3rlvryqdhqfgl","session_start_timestamp":1681363781292,"timestamp":1681363785803,"devicebrand":"Huawei","speed":"117 km/h"}
{"location":{"lat":7.165280222219268,"lng":9.088218829739503},"accuracy":60,"macAddress":"13:BD:B0:D8:2B:35","sessionId":"8ihg17mj18xpbwxf","session_start_timestamp":1681363782283,"timestamp":1681363786801,"devicebrand":"Apple","speed":"85 km/h"}
{"location":{"lat":2.697097802431735,"lng":6.185575497561076},"accuracy":70,"macAddress":"E5:0E:29:AF:45:A3","sessionId":"in1fiffyjjfwr8rb","session_start_timestamp":1681363782964,"timestamp":1681363787116,"devicebrand":"Xiaomi","speed":"68 km/h"}
{"location":{"lat":5.666242557639924,"lng":8.165664988675335},"accuracy":65,"macAddress":"4C:45:65:67:37:71","sessionId":"l879tsheok7hskk4","session_start_timestamp":1681363781702,"timestamp":1681363787870,"devicebrand":"Oppo","speed":"141 km/h"}
{"location":{"lat":7.16587367213623,"lng":9.087914144065133},"accuracy":75,"macAddress":"13:BD:B0:D8:2B:35","sessionId":"8ihg17mj18xpbwxf","session_start_timestamp":1681363782283,"timestamp":1681363788100,"devicebrand":"Apple","speed":"85 km/h"}
{"location":{"lat":7.166193576251772,"lng":9.088824229569315},"accuracy":90,"macAddress":"13:BD:B0:D8:2B:35","sessionId":"8ihg17mj18xpbwxf","session_start_timestamp":1681363782283,"timestamp":1681363788201,"devicebrand":"Apple","speed":"85 km/h"}
{"location":{"lat":7.829949545565252,"lng":5.739891412120372},"accuracy":45,"macAddress":"22:31:0C:4A:EF:ED","sessionId":"e77kg5hye4m5kc5a","session_start_timestamp":1681363780373,"timestamp":1681363788799,"devicebrand":"Xiaomi","speed":"17 km/h"}
{"location":{"lat":7.165206692718243,"lng":9.08836317131041},"accuracy":100,"macAddress":"13:BD:B0:D8:2B:35","sessionId":"8ihg17mj18xpbwxf","session_start_timestamp":1681363782283,"timestamp":1681363789569,"devicebrand":"Apple","speed":"85 km/h"}
{"location":{"lat":7.830610214990888,"lng":5.740053144997845},"accuracy":45,"macAddress":"22:31:0C:4A:EF:ED","sessionId":"e77kg5hye4m5kc5a","session_start_timestamp":1681363780373,"timestamp":1681363790174,"devicebrand":"Xiaomi","speed":"17 km/h"}
{"location":{"lat":7.829726113288114,"lng":5.7395704689377425},"accuracy":40,"macAddress":"22:31:0C:4A:EF:ED","sessionId":"e77kg5hye4m5kc5a","session_start_timestamp":1681363780373,"timestamp":1681363790745,"devicebrand":"Xiaomi","speed":"17 km/h"}
{"location":{"lat":2.8546953929566476,"lng":0.8373624155953948},"accuracy":95,"macAddress":"0F:D4:B0:BA:54:4C","sessionId":"5qqwfwwfyyom18lh","session_start_timestamp":1681363779379,"timestamp":1681363791066,"devicebrand":"Apple","speed":"154 km/h"}
{"location":{"lat":6.811568644132692,"lng":8.326427103692422},"accuracy":85,"macAddress":"F0:B0:31:DD:7C:AA","sessionId":"10i3rlvryqdhqfgl","session_start_timestamp":1681363781292,"timestamp":1681363791614,"devicebrand":"Huawei","speed":"117 km/h"}
{"location":{"lat":7.8290086030490045,"lng":5.738606237173702},"accuracy":35,"macAddress":"22:31:0C:4A:EF:ED","sessionId":"e77kg5hye4m5kc5a","session_start_timestamp":1681363780373,"timestamp":1681363792591,"devicebrand":"Xiaomi","speed":"17 km/h"}
{"location":{"lat":5.665247738891137,"lng":8.165987577968677},"accuracy":50,"macAddress":"4C:45:65:67:37:71","sessionId":"l879tsheok7hskk4","session_start_timestamp":1681363781702,"timestamp":1681363792817,"devicebrand":"Oppo","speed":"141 km/h"}
{"location":{"lat":6.811564841403042,"lng":8.325906286733527},"accuracy":100,"macAddress":"F0:B0:31:DD:7C:AA","sessionId":"10i3rlvryqdhqfgl","session_start_timestamp":1681363781292,"timestamp":1681363792920,"devicebrand":"Huawei","speed":"117 km/h"}
{"location":{"lat":3.1763260782723197,"lng":2.2563745811041276},"accuracy":75,"macAddress":"11:C3:32:C1:10:3D","sessionId":"ff0mu58r724kydod","session_start_timestamp":1681363782786,"timestamp":1681363793301,"devicebrand":"Sony","speed":"71 km/h"}
{"location":{"lat":7.165762866162851,"lng":9.088874692639525},"accuracy":105,"macAddress":"13:BD:B0:D8:2B:35","sessionId":"8ihg17mj18xpbwxf","session_start_timestamp":1681363782283,"timestamp":1681363794249,"devicebrand":"Apple","speed":"85 km/h"}
{"location":{"lat":5.666106520627221,"lng":8.165005464160302},"accuracy":45,"macAddress":"4C:45:65:67:37:71","sessionId":"l879tsheok7hskk4","session_start_timestamp":1681363781702,"timestamp":1681363795060,"devicebrand":"Oppo","speed":"141 km/h"}
{"location":{"lat":7.37759442861437,"lng":9.14246623803365},"accuracy":85,"macAddress":"F7:70:5E:39:C9:06","sessionId":"sstgatr9ezd6lo14","session_start_timestamp":1681363781890,"timestamp":1681363796034,"devicebrand":"Apple","speed":"155 km/h"}
{"location":{"lat":5.665865427370656,"lng":8.165623647732673},"accuracy":35,"macAddress":"4C:45:65:67:37:71","sessionId":"l879tsheok7hskk4","session_start_timestamp":1681363781702,"timestamp":1681363796513,"devicebrand":"Oppo","speed":"141 km/h"}
{"location":{"lat":3.176594779262377,"lng":2.2565045769112473},"accuracy":75,"macAddress":"11:C3:32:C1:10:3D","sessionId":"ff0mu58r724kydod","session_start_timestamp":1681363782786,"timestamp":1681363797379,"devicebrand":"Sony","speed":"71 km/h"}
{"location":{"lat":1.0611494888536175,"lng":2.211392399952261},"accuracy":20,"macAddress":"8A:BB:DE:2E:29:4B","sessionId":"r9a2poiv0zhkebn0","session_start_timestamp":1681363780857,"timestamp":1681363798249,"devicebrand":"LG","speed":"31 km/h"}
{"location":{"lat":2.6979855376784445,"lng":6.186430877006268},"accuracy":70,"macAddress":"E5:0E:29:AF:45:A3","sessionId":"in1fiffyjjfwr8rb","session_start_timestamp":1681363782964,"timestamp":1681363798692,"devicebrand":"Xiaomi","speed":"68 km/h"}
{"location":{"lat":5.665932312581302,"lng":8.166181177486358},"accuracy":50,"macAddress":"4C:45:65:67:37:71","sessionId":"l879tsheok7hskk4","session_start_timestamp":1681363781702,"timestamp":1681363798813,"devicebrand":"Oppo","speed":"141 km/h"}
{"location":{"lat":1.0612961977221023,"lng":2.212370635237859},"accuracy":20,"macAddress":"8A:BB:DE:2E:29:4B","sessionId":"r9a2poiv0zhkebn0","session_start_timestamp":1681363780857,"timestamp":1681363799079,"devicebrand":"LG","speed":"31 km/h"}
{"location":{"lat":5.665496549723977,"lng":8.166407897352393},"accuracy":50,"macAddress":"4C:45:65:67:37:71","sessionId":"l879tsheok7hskk4","session_start_timestamp":1681363781702,"timestamp":1681363799951,"devicebrand":"Oppo","speed":"141 km/h"}
{"location":{"lat":1.0614590535262833,"lng":2.2122309450590856},"accuracy":20,"macAddress":"8A:BB:DE:2E:29:4B","sessionId":"r9a2poiv0zhkebn0","session_start_timestamp":1681363780857,"timestamp":1681363800039,"devicebrand":"LG","speed":"31 km/h"}
{"location":{"lat":3.17745466362225,"lng":2.2562940508877216},"accuracy":75,"macAddress":"11:C3:32:C1:10:3D","sessionId":"ff0mu58r724kydod","session_start_timestamp":1681363782786,"timestamp":1681363800354,"devicebrand":"Sony","speed":"71 km/h"}
{"location":{"lat":2.697235103348672,"lng":6.187374743798296},"accuracy":70,"macAddress":"E5:0E:29:AF:45:A3","sessionId":"in1fiffyjjfwr8rb","session_start_timestamp":1681363782964,"timestamp":1681363801001,"devicebrand":"Xiaomi","speed":"68 km/h"}
{"location":{"lat":6.811430701080966,"lng":8.326020643096887},"accuracy":80,"macAddress":"F0:B0:31:DD:7C:AA","sessionId":"10i3rlvryqdhqfgl","session_start_timestamp":1681363781292,"timestamp":1681363801729,"devicebrand":"Huawei","speed":"117 km/h"}
{"location":{"lat":5.666485882228197,"lng":8.167326109477134},"accuracy":60,"macAddress":"4C:45:65:67:37:71","sessionId":"l879tsheok7hskk4","session_start_timestamp":1681363781702,"timestamp":1681363802489,"devicebrand":"Oppo","speed":"141 km/h"}
{"location":{"lat":7.1662612003805775,"lng":9.088631505111348},"accuracy":115,"macAddress":"13:BD:B0:D8:2B:35","sessionId":"8ihg17mj18xpbwxf","session_start_timestamp":1681363782283,"timestamp":1681363802790,"devicebrand":"Apple","speed":"85 km/h"}
{"location":{"lat":7.166743483684235,"lng":9.088232467098365},"accuracy":115,"macAddress":"13:BD:B0:D8:2B:35","sessionId":"8ihg17mj18xpbwxf","session_start_timestamp":1681363782283,"timestamp":1681363803498,"devicebrand":"Apple","speed":"85 km/h"}
{"location":{"lat":3.1779285591174187,"lng":2.25561484814549},"accuracy":80,"macAddress":"11:C3:32:C1:10:3D","sessionId":"ff0mu58r724kydod","session_start_timestamp":1681363782786,"timestamp":1681363804174,"devicebrand":"Sony","speed":"71 km/h"}
{"location":{"lat":1.060683035727056,"lng":2.2130199514912574},"accuracy":25,"macAddress":"8A:BB:DE:2E:29:4B","sessionId":"r9a2poiv0zhkebn0","session_start_timestamp":1681363780857,"timestamp":1681363804354,"devicebrand":"LG","speed":"31 km/h"}
{"location":{"lat":7.37771168646705,"lng":9.142568515075677},"accuracy":80,"macAddress":"F7:70:5E:39:C9:06","sessionId":"sstgatr9ezd6lo14","session_start_timestamp":1681363781890,"timestamp":1681363804369,"devicebrand":"Apple","speed":"155 km/h"}
{"location":{"lat":5.666860169125767,"lng":8.168300450021588},"accuracy":65,"macAddress":"4C:45:65:67:37:71","sessionId":"l879tsheok7hskk4","session_start_timestamp":1681363781702,"timestamp":1681363805271,"devicebrand":"Oppo","speed":"141 km/h"}
{"location":{"lat":7.166945250567199,"lng":9.087985354941706},"accuracy":110,"macAddress":"13:BD:B0:D8:2B:35","sessionId":"8ihg17mj18xpbwxf","session_start_timestamp":1681363782283,"timestamp":1681363805801,"devicebrand":"Apple","speed":"85 km/h"}
{"location":{"lat":3.178493047212177,"lng":2.2546656502565865},"accuracy":80,"macAddress":"11:C3:32:C1:10:3D","sessionId":"ff0mu58r724kydod","session_start_timestamp":1681363782786,"timestamp":1681363806495,"devicebrand":"Sony","speed":"71 km/h"}
{"location":{"lat":3.1785667843552448,"lng":2.2537688242450384},"accuracy":65,"macAddress":"11:C3:32:C1:10:3D","sessionId":"ff0mu58r724kydod","session_start_timestamp":1681363782786,"timestamp":1681363807084,"devicebrand":"Sony","speed":"71 km/h"}
{"location":{"lat":2.8539086421998174,"lng":0.8373885292772177},"accuracy":90,"macAddress":"0F:D4:B0:BA:54:4C","sessionId":"5qqwfwwfyyom18lh","session_start_timestamp":1681363779379,"timestamp":1681363807210,"devicebrand":"Apple","speed":"154 km/h"}
{"location":{"lat":7.16625721526509,"lng":9.087181906117024},"accuracy":105,"macAddress":"13:BD:B0:D8:2B:35","sessionId":"8ihg17mj18xpbwxf","session_start_timestamp":1681363782283,"timestamp":1681363807584,"devicebrand":"Apple","speed":"85 km/h"}
{"location":{"lat":2.854457163114466,"lng":0.8367438509962748},"accuracy":95,"macAddress":"0F:D4:B0:BA:54:4C","sessionId":"5qqwfwwfyyom18lh","session_start_timestamp":1681363779379,"timestamp":1681363808232,"devicebrand":"Apple","speed":"154 km/h"}
{"location":{"lat":3.1781964914304206,"lng":2.253025747941712},"accuracy":55,"macAddress":"11:C3:32:C1:10:3D","sessionId":"ff0mu58r724kydod","session_start_timestamp":1681363782786,"timestamp":1681363808634,"devicebrand":"Sony","speed":"71 km/h"}
{"location":{"lat":5.667377212945652,"lng":8.167542512922985},"accuracy":75,"macAddress":"4C:45:65:67:37:71","sessionId":"l879tsheok7hskk4","session_start_timestamp":1681363781702,"timestamp":1681363809359,"devicebrand":"Oppo","speed":"141 km/h"}
{"location":{"lat":2.854660996843226,"lng":0.8361808299722727},"accuracy":75,"macAddress":"0F:D4:B0:BA:54:4C","sessionId":"5qqwfwwfyyom18lh","session_start_timestamp":1681363779379,"timestamp":1681363809388,"devicebrand":"Apple","speed":"154 km/h"}
{"location":{"lat":3.1785692869174307,"lng":2.2528258432941435},"accuracy":40,"macAddress":"11:C3:32:C1:10:3D","sessionId":"ff0mu58r724kydod","session_start_timestamp":1681363782786,"timestamp":1681363810305,"devicebrand":"Sony","speed":"71 km/h"}
{"location":{"lat":6.810802743513628,"lng":8.325182928763036},"accuracy":75,"macAddress":"F0:B0:31:DD:7C:AA","sessionId":"10i3rlvryqdhqfgl","session_start_timestamp":1681363781292,"timestamp":1681363810620,"devicebrand":"Huawei","speed":"117 km/h"}
{"location":{"lat":3.178237560488664,"lng":2.2518679332944926},"accuracy":40,"macAddress":"11:C3:32:C1:10:3D","sessionId":"ff0mu58r724kydod","session_start_timestamp":1681363782786,"timestamp":1681363810688,"devicebrand":"Sony","speed":"71 km/h"}
{"location":{"lat":2.8546029239145314,"lng":0.835306903323852},"accuracy":80,"macAddress":"0F:D4:B0:BA:54:4C","sessionId":"5qqwfwwfyyom18lh","session_start_timestamp":1681363779379,"timestamp":1681363811308,"devicebrand":"Apple","speed":"154 km/h"}
{"location":{"lat":6.81048643191532,"lng":8.325233948934681},"accuracy":85,"macAddress":"F0:B0:31:DD:7C:AA","sessionId":"10i3rlvryqdhqfgl","session_start_timestamp":1681363781292,"timestamp":1681363812109,"devicebrand":"Huawei","speed":"117 km/h"}
{"location":{"lat":5.667330614852156,"lng":8.167056821929679},"accuracy":80,"macAddress":"4C:45:65:67:37:71","sessionId":"l879tsheok7hskk4","session_start_timestamp":1681363781702,"timestamp":1681363812520,"devicebrand":"Oppo","speed":"141 km/h"}
{"location":{"lat":7.829577924303848,"lng":5.7384325614453155},"accuracy":20,"macAddress":"22:31:0C:4A:EF:ED","sessionId":"e77kg5hye4m5kc5a","session_start_timestamp":1681363780373,"timestamp":1681363813096,"devicebrand":"Xiaomi","speed":"17 km/h"}
{"location":{"lat":7.16567778447518,"lng":9.086959682295468},"accuracy":120,"macAddress":"13:BD:B0:D8:2B:35","sessionId":"8ihg17mj18xpbwxf","session_start_timestamp":1681363782283,"timestamp":1681363814013,"devicebrand":"Apple","speed":"85 km/h"}
{"location":{"lat":3.1784818411663,"lng":2.251833086942855},"accuracy":40,"macAddress":"11:C3:32:C1:10:3D","sessionId":"ff0mu58r724kydod","session_start_timestamp":1681363782786,"timestamp":1681363814178,"devicebrand":"Sony","speed":"71 km/h"}
{"location":{"lat":2.855450773130318,"lng":0.835891446695115},"accuracy":80,"macAddress":"0F:D4:B0:BA:54:4C","sessionId":"5qqwfwwfyyom18lh","session_start_timestamp":1681363779379,"timestamp":1681363814928,"devicebrand":"Apple","speed":"154 km/h"}
{"location":{"lat":1.0607391998519045,"lng":2.2122824963657894},"accuracy":20,"macAddress":"8A:BB:DE:2E:29:4B","sessionId":"r9a2poiv0zhkebn0","session_start_timestamp":1681363780857,"timestamp":1681363815564,"devicebrand":"LG","speed":"31 km/h"}
{"location":{"lat":2.856028186342785,"lng":0.8365010892634879},"accuracy":90,"macAddress":"0F:D4:B0:BA:54:4C","sessionId":"5qqwfwwfyyom18lh","session_start_timestamp":1681363779379,"timestamp":1681363815833,"devicebrand":"Apple","speed":"154 km/h"}
{"location":{"lat":6.809985961174696,"lng":8.3251163372251},"accuracy":90,"macAddress":"F0:B0:31:DD:7C:AA","sessionId":"10i3rlvryqdhqfgl","session_start_timestamp":1681363781292,"timestamp":1681363816783,"devicebrand":"Huawei","speed":"117 km/h"}
{"location":{"lat":5.667114261876813,"lng":8.166645817367915},"accuracy":80,"macAddress":"4C:45:65:67:37:71","sessionId":"l879tsheok7hskk4","session_start_timestamp":1681363781702,"timestamp":1681363817545,"devicebrand":"Oppo","speed":"141 km/h"}
{"location":{"lat":2.6964901034513864,"lng":6.187824423580029},"accuracy":85,"macAddress":"E5:0E:29:AF:45:A3","sessionId":"in1fiffyjjfwr8rb","session_start_timestamp":1681363782964,"timestamp":1681363817718,"devicebrand":"Xiaomi","speed":"68 km/h"}
{"location":{"lat":5.66705667875682,"lng":8.166691043197643},"accuracy":65,"macAddress":"4C:45:65:67:37:71","sessionId":"l879tsheok7hskk4","session_start_timestamp":1681363781702,"timestamp":1681363817834,"devicebrand":"Oppo","speed":"141 km/h"}
{"location":{"lat":5.667701397064946,"lng":8.167079152793624},"accuracy":70,"macAddress":"4C:45:65:67:37:71","sessionId":"l879tsheok7hskk4","session_start_timestamp":1681363781702,"timestamp":1681363818594,"devicebrand":"Oppo","speed":"141 km/h"}
{"location":{"lat":3.1786864771894954,"lng":2.251642487528918},"accuracy":25,"macAddress":"11:C3:32:C1:10:3D","sessionId":"ff0mu58r724kydod","session_start_timestamp":1681363782786,"timestamp":1681363819469,"devicebrand":"Sony","speed":"71 km/h"}
{"location":{"lat":6.809608491910097,"lng":8.326109305234747},"accuracy":80,"macAddress":"F0:B0:31:DD:7C:AA","sessionId":"10i3rlvryqdhqfgl","session_start_timestamp":1681363781292,"timestamp":1681363819475,"devicebrand":"Huawei","speed":"117 km/h"}
{"location":{"lat":2.6965095181937313,"lng":6.188397999659436},"accuracy":70,"macAddress":"E5:0E:29:AF:45:A3","sessionId":"in1fiffyjjfwr8rb","session_start_timestamp":1681363782964,"timestamp":1681363819704,"devicebrand":"Xiaomi","speed":"68 km/h"}
{"location":{"lat":2.6967043574522007,"lng":6.187730234462691},"accuracy":55,"macAddress":"E5:0E:29:AF:45:A3","sessionId":"in1fiffyjjfwr8rb","session_start_timestamp":1681363782964,"timestamp":1681363820149,"devicebrand":"Xiaomi","speed":"68 km/h"}
{"location":{"lat":2.697363864159704,"lng":6.188548483358991},"accuracy":50,"macAddress":"E5:0E:29:AF:45:A3","sessionId":"in1fiffyjjfwr8rb","session_start_timestamp":1681363782964,"timestamp":1681363820784,"devicebrand":"Xiaomi","speed":"68 km/h"}
{"location":{"lat":5.667829363072988,"lng":8.1672683575508},"accuracy":50,"macAddress":"4C:45:65:67:37:71","sessionId":"l879tsheok7hskk4","session_start_timestamp":1681363781702,"timestamp":1681363821086,"devicebrand":"Oppo","speed":"141 km/h"}
{"location":{"lat":2.6967956086124962,"lng":6.189500079257199},"accuracy":55,"macAddress":"E5:0E:29:AF:45:A3","sessionId":"in1fiffyjjfwr8rb","session_start_timestamp":1681363782964,"timestamp":1681363821797,"devicebrand":"Xiaomi","speed":"68 km/h"}
{"location":{"lat":2.6969976803891416,"lng":6.18951685917201},"accuracy":65,"macAddress":"E5:0E:29:AF:45:A3","sessionId":"in1fiffyjjfwr8rb","session_start_timestamp":1681363782964,"timestamp":1681363821843,"devicebrand":"Xiaomi","speed":"68 km/h"}
{"location":{"lat":2.69728646272721,"lng":6.189355160936278},"accuracy":80,"macAddress":"E5:0E:29:AF:45:A3","sessionId":"in1fiffyjjfwr8rb","session_start_timestamp":1681363782964,"timestamp":1681363822588,"devicebrand":"Xiaomi","speed":"68 km/h"}
{"location":{"lat":7.830535749664586,"lng":5.738533157642097},"accuracy":30,"macAddress":"22:31:0C:4A:EF:ED","sessionId":"e77kg5hye4m5kc5a","session_start_timestamp":1681363780373,"timestamp":1681363823032,"devicebrand":"Xiaomi","speed":"17 km/h"}
{"location":{"lat":2.855315993876787,"lng":0.8370754008826785},"accuracy":80,"macAddress":"0F:D4:B0:BA:54:4C","sessionId":"5qqwfwwfyyom18lh","session_start_timestamp":1681363779379,"timestamp":1681363823442,"devicebrand":"Apple","speed":"154 km/h"}
{"location":{"lat":2.8554077152180932,"lng":0.8373080239006331},"accuracy":80,"macAddress":"0F:D4:B0:BA:54:4C","sessionId":"5qqwfwwfyyom18lh","session_start_timestamp":1681363779379,"timestamp":1681363824137,"devicebrand":"Apple","speed":"154 km/h"}
{"location":{"lat":2.6979620480816258,"lng":6.189210871398059},"accuracy":90,"macAddress":"E5:0E:29:AF:45:A3","sessionId":"in1fiffyjjfwr8rb","session_start_timestamp":1681363782964,"timestamp":1681363824559,"devicebrand":"Xiaomi","speed":"68 km/h"}
{"location":{"lat":2.6985430131181567,"lng":6.188938097953647},"accuracy":90,"macAddress":"E5:0E:29:AF:45:A3","sessionId":"in1fiffyjjfwr8rb","session_start_timestamp":1681363782964,"timestamp":1681363825399,"devicebrand":"Xiaomi","speed":"68 km/h"}
{"location":{"lat":7.377706622853859,"lng":9.143423589198777},"accuracy":80,"macAddress":"F7:70:5E:39:C9:06","sessionId":"sstgatr9ezd6lo14","session_start_timestamp":1681363781890,"timestamp":1681363825660,"devicebrand":"Apple","speed":"155 km/h"}
{"location":{"lat":5.668423990423267,"lng":8.166560171035357},"accuracy":35,"macAddress":"4C:45:65:67:37:71","sessionId":"l879tsheok7hskk4","session_start_timestamp":1681363781702,"timestamp":1681363826279,"devicebrand":"Oppo","speed":"141 km/h"}
{"location":{"lat":5.6679160583655195,"lng":8.167112370107608},"accuracy":40,"macAddress":"4C:45:65:67:37:71","sessionId":"l879tsheok7hskk4","session_start_timestamp":1681363781702,"timestamp":1681363826527,"devicebrand":"Oppo","speed":"141 km/h"}
{"location":{"lat":7.164859836236099,"lng":9.087445315212396},"accuracy":115,"macAddress":"13:BD:B0:D8:2B:35","sessionId":"8ihg17mj18xpbwxf","session_start_timestamp":1681363782283,"timestamp":1681363827274,"devicebrand":"Apple","speed":"85 km/h"}
{"location":{"lat":7.163859911291465,"lng":9.087988494414171},"accuracy":115,"macAddress":"13:BD:B0:D8:2B:35","sessionId":"8ihg17mj18xpbwxf","session_start_timestamp":1681363782283,"timestamp":1681363827740,"devicebrand":"Apple","speed":"85 km/h"}
{"location":{"lat":7.377255175554275,"lng":9.14367057839517},"accuracy":65,"macAddress":"F7:70:5E:39:C9:06","sessionId":"sstgatr9ezd6lo14","session_start_timestamp":1681363781890,"timestamp":1681363827864,"devicebrand":"Apple","speed":"155 km/h"}
{"location":{"lat":7.163783468538323,"lng":9.088065418959934},"accuracy":100,"macAddress":"13:BD:B0:D8:2B:35","sessionId":"8ihg17mj18xpbwxf","session_start_timestamp":1681363782283,"timestamp":1681363827935,"devicebrand":"Apple","speed":"85 km/h"}
{"location":{"lat":2.8552128376996104,"lng":0.8363945763838951},"accuracy":70,"macAddress":"0F:D4:B0:BA:54:4C","sessionId":"5qqwfwwfyyom18lh","session_start_timestamp":1681363779379,"timestamp":1681363827940,"devicebrand":"Apple","speed":"154 km/h"}
{"location":{"lat":6.809522844212907,"lng":8.325862366668071},"accuracy":65,"macAddress":"F0:B0:31:DD:7C:AA","sessionId":"10i3rlvryqdhqfgl","session_start_timestamp":1681363781292,"timestamp":1681363828442,"devicebrand":"Huawei","speed":"117 km/h"}
{"location":{"lat":5.668639608286829,"lng":8.1677142919202},"accuracy":50,"macAddress":"4C:45:65:67:37:71","sessionId":"l879tsheok7hskk4","session_start_timestamp":1681363781702,"timestamp":1681363828448,"devicebrand":"Oppo","speed":"141 km/h"}
{"location":{"lat":6.808642210055141,"lng":8.326510073025243},"accuracy":70,"macAddress":"F0:B0:31:DD:7C:AA","sessionId":"10i3rlvryqdhqfgl","session_start_timestamp":1681363781292,"timestamp":1681363829259,"devicebrand":"Huawei","speed":"117 km/h"}
{"location":{"lat":2.854351472695669,"lng":0.8356912028067003},"accuracy":55,"macAddress":"0F:D4:B0:BA:54:4C","sessionId":"5qqwfwwfyyom18lh","session_start_timestamp":1681363779379,"timestamp":1681363829572,"devicebrand":"Apple","speed":"154 km/h"}
{"location":{"lat":7.830706742179205,"lng":5.73921260609738},"accuracy":25,"macAddress":"22:31:0C:4A:EF:ED","sessionId":"e77kg5hye4m5kc5a","session_start_timestamp":1681363780373,"timestamp":1681363829684,"devicebrand":"Xiaomi","speed":"17 km/h"}
{"location":{"lat":7.376471256885566,"lng":9.144129537219024},"accuracy":65,"macAddress":"F7:70:5E:39:C9:06","sessionId":"sstgatr9ezd6lo14","session_start_timestamp":1681363781890,"timestamp":1681363830144,"devicebrand":"Apple","speed":"155 km/h"}
{"location":{"lat":7.377324822384929,"lng":9.144822849449287},"accuracy":50,"macAddress":"F7:70:5E:39:C9:06","sessionId":"sstgatr9ezd6lo14","session_start_timestamp":1681363781890,"timestamp":1681363830610,"devicebrand":"Apple","speed":"155 km/h"}
{"location":{"lat":1.0604997379645518,"lng":2.2126700356395856},"accuracy":25,"macAddress":"8A:BB:DE:2E:29:4B","sessionId":"r9a2poiv0zhkebn0","session_start_timestamp":1681363780857,"timestamp":1681363830948,"devicebrand":"LG","speed":"31 km/h"}
{"location":{"lat":2.85492316884847,"lng":0.8354463013995522},"accuracy":50,"macAddress":"0F:D4:B0:BA:54:4C","sessionId":"5qqwfwwfyyom18lh","session_start_timestamp":1681363779379,"timestamp":1681363831596,"devicebrand":"Apple","speed":"154 km/h"}
{"location":{"lat":1.059598204717494,"lng":2.2131860864519948},"accuracy":25,"macAddress":"8A:BB:DE:2E:29:4B","sessionId":"r9a2poiv0zhkebn0","session_start_timestamp":1681363780857,"timestamp":1681363831792,"devicebrand":"LG","speed":"31 km/h"}
{"location":{"lat":6.807879353201145,"lng":8.326406962563494},"accuracy":75,"macAddress":"F0:B0:31:DD:7C:AA","sessionId":"10i3rlvryqdhqfgl","session_start_timestamp":1681363781292,"timestamp":1681363831840,"devicebrand":"Huawei","speed":"117 km/h"}
